claude_hook_utils/__init__.py
claude_hook_utils/py.typed
claude_hook_utils/handler/HookHandler.py
claude_hook_utils/handler/__init__.py
claude_hook_utils/inputs/BaseHookInput.py
claude_hook_utils/inputs/PostToolUseInput.py
claude_hook_utils/inputs/PreToolUseInput.py
claude_hook_utils/inputs/__init__.py
claude_hook_utils/logging/HookLogger.py
claude_hook_utils/logging/__init__.py
claude_hook_utils/responses/BaseHookResponse.py
claude_hook_utils/responses/PostToolUseResponse.py
claude_hook_utils/responses/PreToolUseResponse.py
claude_hook_utils/responses/__init__.py
claude_hook_utils-0.3.0.dist-info/METADATA
claude_hook_utils-0.3.0.dist-info/WHEEL
claude_hook_utils-0.3.0.dist-info/licenses/LICENSE
claude_hook_utils-0.3.0.dist-info/RECORD
