Metadata-Version: 2.4
Name: claude-hook-utils
Version: 0.3.0
Summary: Utilities for building Claude Code hooks with minimal boilerplate
Project-URL: Homepage, https://github.com/RasmusGodske/claude-hook-utils
Project-URL: Documentation, https://github.com/RasmusGodske/claude-hook-utils#readme
Project-URL: Repository, https://github.com/RasmusGodske/claude-hook-utils
Project-URL: Issues, https://github.com/RasmusGodske/claude-hook-utils/issues
Project-URL: Changelog, https://github.com/RasmusGodske/claude-hook-utils/releases
Author: Rasmus Godske
Maintainer: Rasmus Godske
License-Expression: MIT
License-File: LICENSE
Keywords: ai,anthropic,automation,claude,claude-code,developer-experience,development-tools,hooks
Classifier: Development Status :: 4 - Beta
Classifier: Intended Audience :: Developers
Classifier: License :: OSI Approved :: MIT License
Classifier: Operating System :: OS Independent
Classifier: Programming Language :: Python :: 3
Classifier: Programming Language :: Python :: 3.10
Classifier: Programming Language :: Python :: 3.11
Classifier: Programming Language :: Python :: 3.12
Classifier: Programming Language :: Python :: 3.13
Classifier: Topic :: Software Development :: Libraries :: Python Modules
Classifier: Topic :: Software Development :: Quality Assurance
Classifier: Typing :: Typed
Requires-Python: >=3.10
Provides-Extra: dev
Requires-Dist: mypy>=1.0; extra == 'dev'
Requires-Dist: pytest-cov>=4.0; extra == 'dev'
Requires-Dist: pytest>=7.0; extra == 'dev'
Requires-Dist: ruff>=0.1; extra == 'dev'
